flexible_rate_limiter/__init__.py
flexible_rate_limiter/main.py
flexible_rate_limiter/models.py
flexible_rate_limiter/py.typed
flexible_rate_limiter-0.1.0.dist-info/METADATA
flexible_rate_limiter-0.1.0.dist-info/WHEEL
flexible_rate_limiter-0.1.0.dist-info/RECORD
