Metadata-Version: 2.4
Name: flexible-rate-limiter
Version: 0.1.0
Summary: A high-performance, Redis-backed rate limiter for FastAPI applications with dynamic rate limits.
Requires-Python: >=3.12
Requires-Dist: fastapi>=0.128.0
Requires-Dist: humanize>=4.15.0
Requires-Dist: pytimeparse>=1.1.8
Requires-Dist: redis>=7.1.0
